MANIFEST.in
RELEASE-VERSION
pavement.py
paver-minilib.zip
setup.py
version.py
arduino_memory/__init__.py
arduino_memory.egg-info/PKG-INFO
arduino_memory.egg-info/SOURCES.txt
arduino_memory.egg-info/dependency_links.txt
arduino_memory.egg-info/pbr.json
arduino_memory.egg-info/top_level.txt
arduino_memory/Arduino/Memory-Arduino.tar.gz
arduino_memory/Arduino/Memory/Memory.h
arduino_memory/lib/Memory-Arduino.tar.gz