Metadata-Version: 1.0
Name: arduino-memory
Version: 0.1.post2
Summary: Simple Arduino library for querying amount of free RAM memory.
Home-page: https://github.com/wheeler-microfluidics/arduino-memory
Author: Christian Fobel
Author-email: christian@fobel.net
License: GPL
Keywords: arduino memory
Platform: UNKNOWN
